pyspark_data_engineering_framework/__init__.py
pyspark_data_engineering_framework/exceptions.py
pyspark_data_engineering_framework/reader.py
pyspark_data_engineering_framework/utils.py
pyspark_data_engineering_framework-0.0.1.dist-info/licenses/LICENSE
tests/__init__.py
tests/test_reader.py
tests/test_utils.py
pyspark_data_engineering_framework-0.0.1.dist-info/METADATA
pyspark_data_engineering_framework-0.0.1.dist-info/WHEEL
pyspark_data_engineering_framework-0.0.1.dist-info/top_level.txt
pyspark_data_engineering_framework-0.0.1.dist-info/RECORD
